Workbook

Sheet Sources
A1: # | B1: Source | C1: Published | D1: What was used
A2: 1 | B2: Concord CPS, Secondary Real Estate Market Analysis: Dhaka 2026 Trends (cites Bproperty 2026 listing data) | C2: 14 Jun 2026 | D2: Average asking price per sq ft by area; 12-month trend; gross rental yield; inflation
A3: 2 | B3: The Business Standard, Housing sector sinks deeper amid plunging sales, soaring costs | C3: 16 Jul 2026 | D3: Directorate of Registration apartment deeds 2023 to H1 2026; construction cost; budget taxes; developer cancellations
A4: 3 | B4: The Daily Star, BB cuts policy rate to 9.5% | C4: 30 Jul 2026 | D4: Policy rate 10% to 9.5% (effective 2 Aug 2026); inflation 9.16% in June 2026
A5: 4 | B5: The Daily Star, Household income doubles in 6 years, so does spending (BBS HIES 2022) | C5: 18 Dec 2023 | D5: Average monthly household income: national Tk 32,422; urban Tk 45,757 (2022)
A6: 5 | B6: Angan Properties, Flat Prices in Dhaka: Area-Wise Rates & Trends | C6: 8 Jan 2026 (updated 14 Mar 2026) | D6: Cross-check only: price ranges are wider and higher than [1]; source of its figures not stated
A7: 6 | B7: BRAC Bank, Base rate page (Bangladesh Bank published data) | C7: Nov 2025 data | D7: Base rate 9.65%; home loan = base rate + bank margin (margin not published on page)
A9: Notes
A10: Asking prices are listing prices, not transaction prices. Registered (declared) values are usually below market value.
A11: Sources partly conflict (for example the Mirpur price trend). The workbook shows the figure from [1] and flags the conflict in the report.
A12: Yellow cells in other sheets are assumptions that can be changed; all results recalculate.
A13: Prepared by Md. Tanjin ul Haque in Excel, with AI assistance for drafting and for checking calculations.

Sheet Formulas_Used
A1: Formulas used in this workbook (column C reads the live formula from the sheet; column E shows its current result)
A2: Sheet | B2: Cell | C2: Live formula | D2: What it does | E2: Result now
A3: Prices | B3: E2 | C3: =_xlfn.FORMULATEXT(Prices!E2) -> =B2/$B$7 | D3: Price of each area as a multiple of Mirpur (the cheapest area). | E3: =Prices!E2 -> 2.1735344
A4: Registrations | B4: D2 | C4: =_xlfn.FORMULATEXT(Registrations!D2) -> =C2*100/B2 | D4: Average declared value per deed, converted from Tk crore to Tk lakh (x100). | E4: =Registrations!D2 -> 68.493151
A5: Registrations | B5: F2 | C5: =_xlfn.FORMULATEXT(Registrations!F2) -> =B2/2 | D5: Puts full years on a half-year basis so they compare fairly with H1 2026. | E5: =Registrations!F2 -> 73000
A6: Registrations | B6: C10 | C6: =_xlfn.FORMULATEXT(Registrations!C10) -> =$B$5/(1+B10) | D6: Backs out the base-period deeds implied by the reported % change. | E6: =Registrations!C10 -> 52001.493
A7: Registrations | B7: D10 | C7: =_xlfn.FORMULATEXT(Registrations!D10) -> =$B$5/C10-1 | D7: Check: recomputes the % change from the implied base; should equal the reported figure. | E7: =Registrations!D10 -> -0.1961
A8: Affordability | B8: C10 | C8: =_xlfn.FORMULATEXT(Affordability!C10) -> =B10*$B$2 | D8: Unit price = price per sq ft x unit size. | E8: =Affordability!C10 -> 11182400
A9: Affordability | B9: D10 | C9: =_xlfn.FORMULATEXT(Affordability!D10) -> =C10*$B$3 | D9: Loan = unit price x share financed. | E9: =Affordability!D10 -> 7827680
A10: Affordability | B10: E10 | C10: =_xlfn.FORMULATEXT(Affordability!E10) -> =-PMT($B$5/12,$B$4*12,D10) | D10: Monthly EMI with PMT(rate per month, number of months, loan). | E10: =Affordability!E10 -> 86189.499
A11: Affordability | B11: F10 | C11: =_xlfn.FORMULATEXT(Affordability!F10) -> =E10/$B$6 | D11: Income needed so that EMI is no more than the chosen share of income. | E11: =Affordability!F10 -> 215473.75
A12: Affordability | B12: G10 | C12: =_xlfn.FORMULATEXT(Affordability!G10) -> =F10/$B$7 | D12: Income needed as a multiple of average urban household income. | E12: =Affordability!G10 -> 4.7090882
A13: Affordability | B13: B20 | C13: =_xlfn.FORMULATEXT(Affordability!B20) -> =-PMT(A20/12,$B$4*12,$D$15) | D13: Same EMI formula, using each scenario interest rate. | E13: =Affordability!B20 -> 39654.076
A14: Automation_Scenarios | B14: B5 | C14: =_xlfn.FORMULATEXT(Automation_Scenarios!B5) -> =AVERAGE(B3:C3)-AVERAGE(B4:C4) | D14: Minutes saved per check = average manual time minus average automated time. | E14: =Automation_Scenarios!B5 -> 11
A15: Automation_Scenarios | B15: C8 | C15: =_xlfn.FORMULATEXT(Automation_Scenarios!C8) -> =B8/60 | D15: Minutes saved per week converted to hours. | E15: =Automation_Scenarios!C8 -> 1.8333333
A16: Automation_Scenarios | B16: D8 | C16: =_xlfn.FORMULATEXT(Automation_Scenarios!D8) -> =C8*4.33 | D16: Hours per week x 4.33 weeks = hours per month. | E16: =Automation_Scenarios!D8 -> 7.9383333
A17: Chat_Log_Fictional | B17: H3 | C17: =_xlfn.FORMULATEXT(Chat_Log_Fictional!H3) -> =IF(SUMPRODUCT(--ISNUMBER(SEARCH($Keywords.B$3:B$7,$D3)))>0,1,0) | D17: Keyword tagging: SEARCH looks for each phrase in the message, SUMPRODUCT counts matches, IF turns it into 1 or 0. | E17: =Chat_Log_Fictional!H3 -> 1
A18: Chat_Log_Fictional | B18: N3 | C18: =_xlfn.FORMULATEXT(Chat_Log_Fictional!N3) -> =SUM(H3:M3) | D18: Number of themes matched by the chat. | E18: =Chat_Log_Fictional!N3 -> 1
A19: Chat_Log_Fictional | B19: O3 | C19: =_xlfn.FORMULATEXT(Chat_Log_Fictional!O3) -> =IF(N3=0,"Other",INDEX($H$2:$M$2,MATCH(1,H3:M3,0))) | D19: First matching theme, or 'Other' when none matched (INDEX + MATCH). | E19: =Chat_Log_Fictional!O3 -> Market data
A20: Keyword_Analysis | B20: B2 | C20: =_xlfn.FORMULATEXT(Keyword_Analysis!B2) -> =COUNTA($Chat_Log_Fictional.$A$3:$A$155) | D20: Total number of chats (COUNTA of the ID column). | E20: =Keyword_Analysis!B2 -> 153
A21: Keyword_Analysis | B21: B5 | C21: =_xlfn.FORMULATEXT(Keyword_Analysis!B5) -> =SUM($Chat_Log_Fictional.$H$3:$H$155) | D21: Chats mentioning the theme (sum of the 1/0 flags). | E21: =Keyword_Analysis!B5 -> 44
A22: Keyword_Analysis | B22: C5 | C22: =_xlfn.FORMULATEXT(Keyword_Analysis!C5) -> =B5/$B$2 | D22: Share of all chats. | E22: =Keyword_Analysis!C5 -> 0.2875817
A23: Keyword_Analysis | B23: D5 | C23: =_xlfn.FORMULATEXT(Keyword_Analysis!D5) -> =SUMPRODUCT($Chat_Log_Fictional.$H$3:$H$155,$Chat_Log_Fictional.$E$3:$E$155)/B5 | D23: Average handle time of chats with the theme (SUMPRODUCT of flag x minutes / count). | E23: =Keyword_Analysis!D5 -> 13.613636
A24: Keyword_Analysis | B24: E5 | C24: =_xlfn.FORMULATEXT(Keyword_Analysis!E5) -> =B5*D5/60 | D24: Total handling hours = chats x average minutes / 60. | E24: =Keyword_Analysis!E5 -> 9.9833333
A25: Keyword_Analysis | B25: F5 | C25: =_xlfn.FORMULATEXT(Keyword_Analysis!F5) -> =SUMPRODUCT($Chat_Log_Fictional.$H$3:$H$155,$Chat_Log_Fictional.$F$3:$F$155)/B5 | D25: Average CSAT of chats with the theme. | E25: =Keyword_Analysis!F5 -> 3.4772727
A26: Keyword_Analysis | B26: G5 | C26: =_xlfn.FORMULATEXT(Keyword_Analysis!G5) -> =SUMPRODUCT($Chat_Log_Fictional.$H$3:$H$155,--($Chat_Log_Fictional.$G$3:$G$155="Y"))/B5 | D26: Repeat-contact rate: chats with the theme and 'Y' / chats with the theme. | E26: =Keyword_Analysis!G5 -> 0.13636364
A27: Keyword_Analysis | B27: H5 | C27: =_xlfn.FORMULATEXT(Keyword_Analysis!H5) -> =E5*(1+G5)*(5-F5) | D27: Pain score = hours x (1 + repeat rate) x (5 - CSAT). Ranking aid only. | E27: =Keyword_Analysis!H5 -> 17.274879
A28: Keyword_Analysis | B28: I5 | C28: =_xlfn.FORMULATEXT(Keyword_Analysis!I5) -> =RANK(H5,$H$5:$H$10) | D28: Rank of the pain score (1 = fix first). | E28: =Keyword_Analysis!I5 -> 2
A29: Keyword_Analysis | B29: B11 | C29: =_xlfn.FORMULATEXT(Keyword_Analysis!B11) -> =COUNTIF($Chat_Log_Fictional.$N$3:$N$155,0) | D29: Chats where no keyword matched (COUNTIF of 0 themes). | E29: =Keyword_Analysis!B11 -> 14
A30: Weekly_Trend | B30: B3 | C30: =_xlfn.FORMULATEXT(Weekly_Trend!B3) -> =SUMIFS($Chat_Log_Fictional.$H$3:$H$155,$Chat_Log_Fictional.$B$3:$B$155,$A3) | D30: Chats per week for a theme (SUMIFS on the flag column and the week). | E30: =Weekly_Trend!B3 -> 3
A31: Weekly_Trend | B31: B14 | C31: =_xlfn.FORMULATEXT(Weekly_Trend!B14) -> =B13/B12 | D31: Weeks 5-7 average divided by weeks 1-4 average. | E31: =Weekly_Trend!B14 -> 2.4761905
A32: Weekly_Trend | B32: B15 | C32: =_xlfn.FORMULATEXT(Weekly_Trend!B15) -> =IF(B14>1.5,"Investigate","Normal") | D32: Alert if the rise is over 1.5x. | E32: =Weekly_Trend!B15 -> Investigate
A33: Product_Roadmap | B33: B4 | C33: =_xlfn.FORMULATEXT(Product_Roadmap!B4) -> =$Keyword_Analysis.B5&" of "&$Keyword_Analysis.$B$2&" chats ("&TEXT($Keyword_Analysis.C5,"0%")&"), avg CSAT "&TEXT($Keyword_Analysis.F5,"0.0") | D33: Builds a sentence from live numbers (text joined with &, TEXT for formatting). | E33: =Product_Roadmap!B4 -> 44 of 153 chats (29%), avg CSAT 3.5
A34: Product_Roadmap | B34: E4 | C34: =_xlfn.FORMULATEXT(Product_Roadmap!E4) -> =$Keyword_Analysis.B5/8*D4 | D34: Chats avoided per week = chats / 8 weeks x assumed reduction. | E34: =Product_Roadmap!E4 -> 2.2
A35: Product_Roadmap | B35: F4 | C35: =_xlfn.FORMULATEXT(Product_Roadmap!F4) -> =E4*$Keyword_Analysis.D5/60 | D35: Hours saved per week = chats avoided x average minutes / 60. | E35: =Product_Roadmap!F4 -> 0.49916667

Sheet Prices
A1: Area | B1: Avg asking price (Tk per sq ft) | C1: Gross rental yield (%) | D1: 12-month trend (as stated in [1]) | E1: Price vs Mirpur (x) | F1: Source
A2: Gulshan | B2: 13978 | C2: 4.7 | D2: Strong positive | E2: =B2/$B$7 -> 2.1735344 | F2: [1]
A3: Banani | B3: 13684 | C3: 3.8 | D3: Positive | E3: =B3/$B$7 -> 2.1278184 | F3: [1]
A4: Dhanmondi | B4: 12289 | C4: 2.7 | D4: Slightly negative / stable | E4: =B4/$B$7 -> 1.9109003 | F4: [1]
A5: Bashundhara | B5: 9894 | C5: 3.25 | D5: Negative | E5: =B5/$B$7 -> 1.5384855 | F5: [1]
A6: Uttara | B6: 8925 | C6: 3.25 | D6: Mild positive | E6: =B6/$B$7 -> 1.387809 | F6: [1]
A7: Mirpur | B7: 6431 | C7: 4.5 | D7: Negative | E7: =B7/$B$7 -> 1 | F7: [1]
A9: Uttara and Bashundhara yields are given as a 3.2% to 3.3% range in [1]; 3.25% is the midpoint.

Sheet Registrations
A1: Period | B1: Apartment deeds | C1: Declared value (Tk crore) | D1: Avg declared value per deed (Tk lakh) | E1: Note | F1: Deeds per half-year (for fair chart)
A2: 2023 | B2: 146000 | C2: 100000 | D2: =C2*100/B2 -> 68.493151 | E2: Full year | F2: =B2/2 -> 73000
A3: 2024 | B3: 112000 | C3: 79000 | D3: =C3*100/B3 -> 70.535714 | E3: Full year | F3: =B3/2 -> 56000
A4: 2025 | B4: 104000 | C4: 61000 | D4: =C4*100/B4 -> 58.653846 | E4: Full year | F4: =B4/2 -> 52000
A5: H1 2026 (Jan-Jun) | B5: 41804 | C5: 18000 | D5: =C5*100/B5 -> 43.058081 | E5: Half year; Dhaka accounted for 29,913 | F5: =B5 -> 41804
A8: H1 2026 change vs (as reported in [2])
A9: Comparison | B9: Reported change | C9: Implied base deeds | D9: Check: H1 2026 / base - 1
A10: 2025 half-year average | B10: -0.1961 | C10: =$B$5/(1+B10) -> 52001.493 | D10: =$B$5/C10-1 -> -0.1961
A11: Jan-Jun 2024 | B11: -0.2535 | C11: =$B$5/(1+B11) -> 56000 | D11: =$B$5/C11-1 -> -0.2535
A12: Jan-Jun 2023 | B12: -0.4273 | C12: =$B$5/(1+B12) -> 72994.587 | D12: =$B$5/C12-1 -> -0.4273
A14: Declared values are registration values, not market prices. Source: Directorate of Registration, as reported in [2].

Sheet Affordability
A1: Assumptions (yellow cells can be changed)
A2: Unit size (sq ft) | B2: 800
A3: Share of price financed by loan | B3: 0.7
A4: Loan tenure (years) | B4: 20
A5: Loan interest rate (annual) | B5: 0.12
A6: Max EMI as share of monthly household income | B6: 0.4
A7: Reference: avg urban household income, Tk per month (HIES 2022) [4] | B7: 45757
A9: Area | B9: Price per sq ft | C9: Unit price (Tk) | D9: Loan (Tk) | E9: Monthly EMI (Tk) | F9: Income needed per month (Tk) | G9: Multiple of avg urban household income | H9: Avg urban household income (reference)
A10: Gulshan | B10: =Prices!B2 -> 13978 | C10: =B10*$B$2 -> 11182400 | D10: =C10*$B$3 -> 7827680 | E10: =-PMT($B$5/12,$B$4*12,D10) -> 86189.499 | F10: =E10/$B$6 -> 215473.75 | G10: =F10/$B$7 -> 4.7090882 | H10: =$B$7 -> 45757
A11: Banani | B11: =Prices!B3 -> 13684 | C11: =B11*$B$2 -> 10947200 | D11: =C11*$B$3 -> 7663040 | E11: =-PMT($B$5/12,$B$4*12,D11) -> 84376.671 | F11: =E11/$B$6 -> 210941.68 | G11: =F11/$B$7 -> 4.6100417 | H11: =$B$7 -> 45757
A12: Dhanmondi | B12: =Prices!B4 -> 12289 | C12: =B12*$B$2 -> 9831200 | D12: =C12*$B$3 -> 6881840 | E12: =-PMT($B$5/12,$B$4*12,D12) -> 75774.986 | F12: =E12/$B$6 -> 189437.46 | G12: =F12/$B$7 -> 4.1400762 | H12: =$B$7 -> 45757
A13: Bashundhara | B13: =Prices!B5 -> 9894 | C13: =B13*$B$2 -> 7915200 | D13: =C13*$B$3 -> 5540640 | E13: =-PMT($B$5/12,$B$4*12,D13) -> 61007.219 | F13: =E13/$B$6 -> 152518.05 | G13: =F13/$B$7 -> 3.3332178 | H13: =$B$7 -> 45757
A14: Uttara | B14: =Prices!B6 -> 8925 | C14: =B14*$B$2 -> 7140000 | D14: =C14*$B$3 -> 4998000 | E14: =-PMT($B$5/12,$B$4*12,D14) -> 55032.285 | F14: =E14/$B$6 -> 137580.71 | G14: =F14/$B$7 -> 3.0067686 | H14: =$B$7 -> 45757
A15: Mirpur | B15: =Prices!B7 -> 6431 | C15: =B15*$B$2 -> 5144800 | D15: =C15*$B$3 -> 3601360 | E15: =-PMT($B$5/12,$B$4*12,D15) -> 39654.076 | F15: =E15/$B$6 -> 99135.189 | G15: =F15/$B$7 -> 2.1665579 | H15: =$B$7 -> 45757
A17: Rate sensitivity: income needed per month for a Mirpur-priced unit
A18: Interest rate | B18: Monthly EMI (Tk) | C18: Income needed per month (Tk)
A19: 0.1 | B19: =-PMT(A19/12,$B$4*12,$D$15) -> 34753.904 | C19: =B19/$B$6 -> 86884.759
A20: 0.12 | B20: =-PMT(A20/12,$B$4*12,$D$15) -> 39654.076 | C20: =B20/$B$6 -> 99135.189
A21: 0.14 | B21: =-PMT(A21/12,$B$4*12,$D$15) -> 44783.661 | C21: =B21/$B$6 -> 111959.15
A23: Interest rate context: policy rate cut to 9.5% from 10% (effective 2 Aug 2026) [3]; a bank base rate of 9.65% (Nov 2025) [6]. A home loan adds a bank margin, so 10% to 14% is used as a scenario range, not a quoted rate.
A24: Income reference is 2022 data and incomes have risen since; inflation was 9.16% in June 2026 [3]. Treat the multiple as indicative.

Sheet Automation_Scenarios
A1: Time saved by the automation: scenarios (replace the yellow cells with real counts)
A3: Manual time per check, minutes (low / high) | B3: 12 | C3: 15
A4: Automated time per check, minutes (low / high) | B4: 2 | C4: 3
A5: Minutes saved per check (midpoint) | B5: =AVERAGE(B3:C3)-AVERAGE(B4:C4) -> 11
A7: Checks per week (scenario) | B7: Minutes saved per week | C7: Hours saved per week | D7: Hours saved per month (4.33 weeks)
A8: 10 | B8: =A8*$B$5 -> 110 | C8: =B8/60 -> 1.8333333 | D8: =C8*4.33 -> 7.9383333
A9: 25 | B9: =A9*$B$5 -> 275 | C9: =B9/60 -> 4.5833333 | D9: =C9*4.33 -> 19.845833
A10: 50 | B10: =A10*$B$5 -> 550 | C10: =B10/60 -> 9.1666667 | D10: =C10*4.33 -> 39.691667
A11: 100 | B11: =A11*$B$5 -> 1100 | C11: =B11/60 -> 18.333333 | D11: =C11*4.33 -> 79.383333
A13: These are scenarios, not reported results. The real number of checks per week is needed to state actual hours saved.

Sheet Keywords
A1: Keyword dictionary (FICTIONAL, editable). Each theme is a list of phrases; a chat is tagged to a theme if its text contains any phrase.
A2: Phrase # | B2: Market data | C2: Account status | D2: Closure or limit reason | E2: Payout or review | F2: Sign-in or verification | G2: Platform setup
A3: 1 | B3: blank chart | C3: which account | D3: why was my account closed | E3: payout | F3: can't log in | G3: how do i
A4: 2 | B4: no prices | C4: on hold | D4: breached | E4: withdrawal | F4: verification | G4: setup
A5: 3 | B5: market data | C5: active accounts | D5: drawdown | E5: review | F5: password | G5: install
A6: 4 | B6: delayed | C6: can't find my account | D6: rule violation | E6: how long | F6: 2fa | G6: connect
A7: 5 | B7: no data | C7: account status | D7: daily loss | E7: pending | F7: email code | G7: download

Sheet Chat_Log_Fictional
A1: FICTIONAL sample: 153 trader chats over 8 weeks (no real client or conversation). Columns H to M are formulas that tag each chat by keyword.
A2: Chat ID | B2: Week | C2: Client stage | D2: Message (fictional) | E2: Handle time (min) | F2: CSAT (1-5) | G2: Repeat contact (Y/N) | H2: Market data | I2: Account status | J2: Closure or limit reason | K2: Payout or review | L2: Sign-in or verification | M2: Platform setup | N2: Themes matched | O2: Primary theme
A3: C001 | B3: 1 | C3: Active | D3: Hello, where can i enable market data in the platform settings? | E3: 15 | F3: 5 | G3: N | H3: =IF(SUMPRODUCT(--ISNUMBER(SEARCH(Keywords!B$3:B$7,$D3)))>0,1,0) -> 1 | I3: =IF(SUMPRODUCT(--ISNUMBER(SEARCH(Keywords!C$3:C$7,$D3)))>0,1,0) -> 0 | J3: =IF(SUMPRODUCT(--ISNUMBER(SEARCH(Keywords!D$3:D$7,$D3)))>0,1,0) -> 0 | K3: =IF(SUMPRODUCT(--ISNUMBER(SEARCH(Keywords!E$3:E$7,$D3)))>0,1,0) -> 0 | L3: =IF(SUMPRODUCT(--ISNUMBER(SEARCH(Keywords!F$3:F$7,$D3)))>0,1,0) -> 0 | M3: =IF(SUMPRODUCT(--ISNUMBER(SEARCH(Keywords!G$3:G$7,$D3)))>0,1,0) -> 0 | N3: =SUM(H3:M3) -> 1 | O3: =IF(N3=0,"Other",INDEX($H$2:$M$2,MATCH(1,H3:M3,0))) -> Market data
A4: C002 | B4: 1 | C4: Active | D4: Hey there, where can i enable market data in the platform settings? | E4: 8 | F4: 2 | G4: Y | H4: =IF(SUMPRODUCT(--ISNUMBER(SEARCH(Keywords!B$3:B$7,$D4)))>0,1,0) -> 1 | I4: =IF(SUMPRODUCT(--ISNUMBER(SEARCH(Keywords!C$3:C$7,$D4)))>0,1,0) -> 0 | J4: =IF(SUMPRODUCT(--ISNUMBER(SEARCH(Keywords!D$3:D$7,$D4)))>0,1,0) -> 0 | K4: =IF(SUMPRODUCT(--ISNUMBER(SEARCH(Keywords!E$3:E$7,$D4)))>0,1,0) -> 0 | L4: =IF(SUMPRODUCT(--ISNUMBER(SEARCH(Keywords!F$3:F$7,$D4)))>0,1,0) -> 0 | M4: =IF(SUMPRODUCT(--ISNUMBER(SEARCH(Keywords!G$3:G$7,$D4)))>0,1,0) -> 0 | N4: =SUM(H4:M4) -> 1 | O4: =IF(N4=0,"Other",INDEX($H$2:$M$2,MATCH(1,H4:M4,0))) -> Market data
A5: C003 | B5: 1 | C5: Active | D5: Hello, one of my accounts is on hold, why? | E5: 14 | F5: 4 | G5: N | H5: =IF(SUMPRODUCT(--ISNUMBER(SEARCH(Keywords!B$3:B$7,$D5)))>0,1,0) -> 0 | I5: =IF(SUMPRODUCT(--ISNUMBER(SEARCH(Keywords!C$3:C$7,$D5)))>0,1,0) -> 1 | J5: =IF(SUMPRODUCT(--ISNUMBER(SEARCH(Keywords!D$3:D$7,$D5)))>0,1,0) -> 0 | K5: =IF(SUMPRODUCT(--ISNUMBER(SEARCH(Keywords!E$3:E$7,$D5)))>0,1,0) -> 0 | L5: =IF(SUMPRODUCT(--ISNUMBER(SEARCH(Keywords!F$3:F$7,$D5)))>0,1,0) -> 0 | M5: =IF(SUMPRODUCT(--ISNUMBER(SEARCH(Keywords!G$3:G$7,$D5)))>0,1,0) -> 0 | N5: =SUM(H5:M5) -> 1 | O5: =IF(N5=0,"Other",INDEX($H$2:$M$2,MATCH(1,H5:M5,0))) -> Account status
A6: C004 | B6: 1 | C6: Active | D6: Hey there, what is the account status of my passed accounts?. also, the verification step keeps failing | E6: 6 | F6: 5 | G6: N | H6: =IF(SUMPRODUCT(--ISNUMBER(SEARCH(Keywords!B$3:B$7,$D6)))>0,1,0) -> 0 | I6: =IF(SUMPRODUCT(--ISNUMBER(SEARCH(Keywords!C$3:C$7,$D6)))>0,1,0) -> 1 | J6: =IF(SUMPRODUCT(--ISNUMBER(SEARCH(Keywords!D$3:D$7,$D6)))>0,1,0) -> 0 | K6: =IF(SUMPRODUCT(--ISNUMBER(SEARCH(Keywords!E$3:E$7,$D6)))>0,1,0) -> 0 | L6: =IF(SUMPRODUCT(--ISNUMBER(SEARCH(Keywords!F$3:F$7,$D6)))>0,1,0) -> 1 | M6: =IF(SUMPRODUCT(--ISNUMBER(SEARCH(Keywords!G$3:G$7,$D6)))>0,1,0) -> 0 | N6: =SUM(H6:M6) -> 2 | O6: =IF(N6=0,"Other",INDEX($H$2:$M$2,MATCH(1,H6:M6,0))) -> Account status
A7: C005 | B7: 1 | C7: New | D7: Hello, i need help with the setup of my second monitor layout | E7: 7 | F7: 5 | G7: Y | H7: =IF(SUMPRODUCT(--ISNUMBER(SEARCH(Keywords!B$3:B$7,$D7)))>0,1,0) -> 0 | I7: =IF(SUMPRODUCT(--ISNUMBER(SEARCH(Keywords!C$3:C$7,$D7)))>0,1,0) -> 0 | J7: =IF(SUMPRODUCT(--ISNUMBER(SEARCH(Keywords!D$3:D$7,$D7)))>0,1,0) -> 0 | K7: =IF(SUMPRODUCT(--ISNUMBER(SEARCH(Keywords!E$3:E$7,$D7)))>0,1,0) -> 0 | L7: =IF(SUMPRODUCT(--ISNUMBER(SEARCH(Keywords!F$3:F$7,$D7)))>0,1,0) -> 0 | M7: =IF(SUMPRODUCT(--ISNUMBER(SEARCH(Keywords!G$3:G$7,$D7)))>0,1,0) -> 1 | N7: =SUM(H7:M7) -> 1 | O7: =IF(N7=0,"Other",INDEX($H$2:$M$2,MATCH(1,H7:M7,0))) -> Platform setup
A8: C006 | B8: 1 | C8: Active | D8: Hey there, why was my account closed? i did not see any warning | E8: 28 | F8: 2 | G8: Y | H8: =IF(SUMPRODUCT(--ISNUMBER(SEARCH(Keywords!B$3:B$7,$D8)))>0,1,0) -> 0 | I8: =IF(SUMPRODUCT(--ISNUMBER(SEARCH(Keywords!C$3:C$7,$D8)))>0,1,0) -> 0 | J8: =IF(SUMPRODUCT(--ISNUMBER(SEARCH(Keywords!D$3:D$7,$D8)))>0,1,0) -> 1 | K8: =IF(SUMPRODUCT(--ISNUMBER(SEARCH(Keywords!E$3:E$7,$D8)))>0,1,0) -> 0 | L8: =IF(SUMPRODUCT(--ISNUMBER(SEARCH(Keywords!F$3:F$7,$D8)))>0,1,0) -> 0 | M8: =IF(SUMPRODUCT(--ISNUMBER(SEARCH(Keywords!G$3:G$7,$D8)))>0,1,0) -> 0 | N8: =SUM(H8:M8) -> 1 | O8: =IF(N8=0,"Other",INDEX($H$2:$M$2,MATCH(1,H8:M8,0))) -> Closure or limit reason
A9: C007 | B9: 1 | C9: New | D9: Hey there, i want to give feedback on the support team | E9: 5 | F9: 4 | G9: N | H9: =IF(SUMPRODUCT(--ISNUMBER(SEARCH(Keywords!B$3:B$7,$D9)))>0,1,0) -> 0 | I9: =IF(SUMPRODUCT(--ISNUMBER(SEARCH(Keywords!C$3:C$7,$D9)))>0,1,0) -> 0 | J9: =IF(SUMPRODUCT(--ISNUMBER(SEARCH(Keywords!D$3:D$7,$D9)))>0,1,0) -> 0 | K9: =IF(SUMPRODUCT(--ISNUMBER(SEARCH(Keywords!E$3:E$7,$D9)))>0,1,0) -> 0 | L9: =IF(SUMPRODUCT(--ISNUMBER(SEARCH(Keywords!F$3:F$7,$D9)))>0,1,0) -> 0 | M9: =IF(SUMPRODUCT(--ISNUMBER(SEARCH(Keywords!G$3:G$7,$D9)))>0,1,0) -> 0 | N9: =SUM(H9:M9) -> 0 | O9: =IF(N9=0,"Other",INDEX($H$2:$M$2,MATCH(1,H9:M9,0))) -> Other
A10: C008 | B10: 1 | C10: Active | D10: Hi, how many active accounts can i have at the same time? | E10: 18 | F10: 4 | G10: N | H10: =IF(SUMPRODUCT(--ISNUMBER(SEARCH(Keywords!B$3:B$7,$D10)))>0,1,0) -> 0 | I10: =IF(SUMPRODUCT(--ISNUMBER(SEARCH(Keywords!C$3:C$7,$D10)))>0,1,0) -> 1 | J10: =IF(SUMPRODUCT(--ISNUMBER(SEARCH(Keywords!D$3:D$7,$D10)))>0,1,0) -> 0 | K10: =IF(SUMPRODUCT(--ISNUMBER(SEARCH(Keywords!E$3:E$7,$D10)))>0,1,0) -> 0 | L10: =IF(SUMPRODUCT(--ISNUMBER(SEARCH(Keywords!F$3:F$7,$D10)))>0,1,0) -> 0 | M10: =IF(SUMPRODUCT(--ISNUMBER(SEARCH(Keywords!G$3:G$7,$D10)))>0,1,0) -> 0 | N10: =SUM(H10:M10) -> 1 | O10: =IF(N10=0,"Other",INDEX($H$2:$M$2,MATCH(1,H10:M10,0))) -> Account status
A11: C009 | B11: 1 | C11: Active | D11: Good evening, where can i enable market data in the platform settings? | E11: 15 | F11: 4 | G11: Y | H11: =IF(SUMPRODUCT(--ISNUMBER(SEARCH(Keywords!B$3:B$7,$D11)))>0,1,0) -> 1 | I11: =IF(SUMPRODUCT(--ISNUMBER(SEARCH(Keywords!C$3:C$7,$D11)))>0,1,0) -> 0 | J11: =IF(SUMPRODUCT(--ISNUMBER(SEARCH(Keywords!D$3:D$7,$D11)))>0,1,0) -> 0 | K11: =IF(SUMPRODUCT(--ISNUMBER(SEARCH(Keywords!E$3:E$7,$D11)))>0,1,0) -> 0 | L11: =IF(SUMPRODUCT(--ISNUMBER(SEARCH(Keywords!F$3:F$7,$D11)))>0,1,0) -> 0 | M11: =IF(SUMPRODUCT(--ISNUMBER(SEARCH(Keywords!G$3:G$7,$D11)))>0,1,0) -> 0 | N11: =SUM(H11:M11) -> 1 | O11: =IF(N11=0,"Other",INDEX($H$2:$M$2,MATCH(1,H11:M11,0))) -> Market data
A12: C010 | B12: 1 | C12: Active | D12: Hey there, the review for my account has been open since monday | E12: 12 | F12: 3 | G12: Y | H12: =IF(SUMPRODUCT(--ISNUMBER(SEARCH(Keywords!B$3:B$7,$D12)))>0,1,0) -> 0 | I12: =IF(SUMPRODUCT(--ISNUMBER(SEARCH(Keywords!C$3:C$7,$D12)))>0,1,0) -> 0 | J12: =IF(SUMPRODUCT(--ISNUMBER(SEARCH(Keywords!D$3:D$7,$D12)))>0,1,0) -> 0 | K12: =IF(SUMPRODUCT(--ISNUMBER(SEARCH(Keywords!E$3:E$7,$D12)))>0,1,0) -> 1 | L12: =IF(SUMPRODUCT(--ISNUMBER(SEARCH(Keywords!F$3:F$7,$D12)))>0,1,0) -> 0 | M12: =IF(SUMPRODUCT(--ISNUMBER(SEARCH(Keywords!G$3:G$7,$D12)))>0,1,0) -> 0 | N12: =SUM(H12:M12) -> 1 | O12: =IF(N12=0,"Other",INDEX($H$2:$M$2,MATCH(1,H12:M12,0))) -> Payout or review
A13: C011 | B13: 1 | C13: Active | D13: Good evening, my account breached but i think the calculation is wrong | E13: 20 | F13: 3 | G13: N | H13: =IF(SUMPRODUCT(--ISNUMBER(SEARCH(Keywords!B$3:B$7,$D13)))>0,1,0) -> 0 | I13: =IF(SUMPRODUCT(--ISNUMBER(SEARCH(Keywords!C$3:C$7,$D13)))>0,1,0) -> 0 | J13: =IF(SUMPRODUCT(--ISNUMBER(SEARCH(Keywords!D$3:D$7,$D13)))>0,1,0) -> 1 | K13: =IF(SUMPRODUCT(--ISNUMBER(SEARCH(Keywords!E$3:E$7,$D13)))>0,1,0) -> 0 | L13: =IF(SUMPRODUCT(--ISNUMBER(SEARCH(Keywords!F$3:F$7,$D13)))>0,1,0) -> 0 | M13: =IF(SUMPRODUCT(--ISNUMBER(SEARCH(Keywords!G$3:G$7,$D13)))>0,1,0) -> 0 | N13: =SUM(H13:M13) -> 1 | O13: =IF(N13=0,"Other",INDEX($H$2:$M$2,MATCH(1,H13:M13,0))) -> Closure or limit reason
A14: C012 | B14: 1 | C14: Active | D14: Hey there, how long does the payout review take? | E14: 8 | F14: 4 | G14: Y | H14: =IF(SUMPRODUCT(--ISNUMBER(SEARCH(Keywords!B$3:B$7,$D14)))>0,1,0) -> 0 | I14: =IF(SUMPRODUCT(--ISNUMBER(SEARCH(Keywords!C$3:C$7,$D14)))>0,1,0) -> 0 | J14: =IF(SUMPRODUCT(--ISNUMBER(SEARCH(Keywords!D$3:D$7,$D14)))>0,1,0) -> 0 | K14: =IF(SUMPRODUCT(--ISNUMBER(SEARCH(Keywords!E$3:E$7,$D14)))>0,1,0) -> 1 | L14: =IF(SUMPRODUCT(--ISNUMBER(SEARCH(Keywords!F$3:F$7,$D14)))>0,1,0) -> 0 | M14: =IF(SUMPRODUCT(--ISNUMBER(SEARCH(Keywords!G$3:G$7,$D14)))>0,1,0) -> 0 | N14: =SUM(H14:M14) -> 1 | O14: =IF(N14=0,"Other",INDEX($H$2:$M$2,MATCH(1,H14:M14,0))) -> Payout or review
... A155: C153 | B155: 8 | C155: Active | D155: Good evening, how long until the withdrawal reaches my bank? | E155: 12 | F155: 4 | G155: N | H155: =IF(SUMPRODUCT(--ISNUMBER(SEARCH(Keywords!B$3:B$7,$D155)))>0,1,0) -> 0 | I155: =IF(SUMPRODUCT(--ISNUMBER(SEARCH(Keywords!C$3:C$7,$D155)))>0,1,0) -> 0 | J155: =IF(SUMPRODUCT(--ISNUMBER(SEARCH(Keywords!D$3:D$7,$D155)))>0,1,0) -> 0 | K155: =IF(SUMPRODUCT(--ISNUMBER(SEARCH(Keywords!E$3:E$7,$D155)))>0,1,0) -> 1 | L155: =IF(SUMPRODUCT(--ISNUMBER(SEARCH(Keywords!F$3:F$7,$D155)))>0,1,0) -> 0 | M155: =IF(SUMPRODUCT(--ISNUMBER(SEARCH(Keywords!G$3:G$7,$D155)))>0,1,0) -> 0 | N155: =SUM(H155:M155) -> 1 | O155: =IF(N155=0,"Other",INDEX($H$2:$M$2,MATCH(1,H155:M155,0))) -> Payout or review

Sheet Keyword_Analysis
A1: Keyword analysis: which themes cost clients and the team the most (fictional data)
A2: Total chats | B2: =COUNTA(Chat_Log_Fictional!$A$3:$A$155) -> 153
A4: Theme | B4: Chats mentioning | C4: Share of chats | D4: Avg handle time (min) | E4: Total handling (hours) | F4: Avg CSAT | G4: Repeat-contact rate | H4: Pain score | I4: Rank
A5: Market data | B5: =SUM(Chat_Log_Fictional!$H$3:$H$155) -> 44 | C5: =B5/$B$2 -> 0.2875817 | D5: =SUMPRODUCT(Chat_Log_Fictional!$H$3:$H$155,Chat_Log_Fictional!$E$3:$E$155)/B5 -> 13.613636 | E5: =B5*D5/60 -> 9.9833333 | F5: =SUMPRODUCT(Chat_Log_Fictional!$H$3:$H$155,Chat_Log_Fictional!$F$3:$F$155)/B5 -> 3.4772727 | G5: =SUMPRODUCT(Chat_Log_Fictional!$H$3:$H$155,--(Chat_Log_Fictional!$G$3:$G$155="Y"))/B5 -> 0.13636364 | H5: =E5*(1+G5)*(5-F5) -> 17.274879 | I5: =RANK(H5,$H$5:$H$10) -> 2
A6: Account status | B6: =SUM(Chat_Log_Fictional!$I$3:$I$155) -> 26 | C6: =B6/$B$2 -> 0.16993464 | D6: =SUMPRODUCT(Chat_Log_Fictional!$I$3:$I$155,Chat_Log_Fictional!$E$3:$E$155)/B6 -> 12.384615 | E6: =B6*D6/60 -> 5.3666667 | F6: =SUMPRODUCT(Chat_Log_Fictional!$I$3:$I$155,Chat_Log_Fictional!$F$3:$F$155)/B6 -> 4.1153846 | G6: =SUMPRODUCT(Chat_Log_Fictional!$I$3:$I$155,--(Chat_Log_Fictional!$G$3:$G$155="Y"))/B6 -> 0.23076923 | H6: =E6*(1+G6)*(5-F6) -> 5.842998 | I6: =RANK(H6,$H$5:$H$10) -> 4
A7: Closure or limit reason | B7: =SUM(Chat_Log_Fictional!$J$3:$J$155) -> 23 | C7: =B7/$B$2 -> 0.1503268 | D7: =SUMPRODUCT(Chat_Log_Fictional!$J$3:$J$155,Chat_Log_Fictional!$E$3:$E$155)/B7 -> 17.173913 | E7: =B7*D7/60 -> 6.5833333 | F7: =SUMPRODUCT(Chat_Log_Fictional!$J$3:$J$155,Chat_Log_Fictional!$F$3:$F$155)/B7 -> 2.2608696 | G7: =SUMPRODUCT(Chat_Log_Fictional!$J$3:$J$155,--(Chat_Log_Fictional!$G$3:$G$155="Y"))/B7 -> 0.30434783 | H7: =E7*(1+G7)*(5-F7) -> 23.520794 | I7: =RANK(H7,$H$5:$H$10) -> 1
A8: Payout or review | B8: =SUM(Chat_Log_Fictional!$K$3:$K$155) -> 23 | C8: =B8/$B$2 -> 0.1503268 | D8: =SUMPRODUCT(Chat_Log_Fictional!$K$3:$K$155,Chat_Log_Fictional!$E$3:$E$155)/B8 -> 11.130435 | E8: =B8*D8/60 -> 4.2666667 | F8: =SUMPRODUCT(Chat_Log_Fictional!$K$3:$K$155,Chat_Log_Fictional!$F$3:$F$155)/B8 -> 3.6086957 | G8: =SUMPRODUCT(Chat_Log_Fictional!$K$3:$K$155,--(Chat_Log_Fictional!$G$3:$G$155="Y"))/B8 -> 0.34782609 | H8: =E8*(1+G8)*(5-F8) -> 8.0010082 | I8: =RANK(H8,$H$5:$H$10) -> 3
A9: Sign-in or verification | B9: =SUM(Chat_Log_Fictional!$L$3:$L$155) -> 13 | C9: =B9/$B$2 -> 0.08496732 | D9: =SUMPRODUCT(Chat_Log_Fictional!$L$3:$L$155,Chat_Log_Fictional!$E$3:$E$155)/B9 -> 9.2307692 | E9: =B9*D9/60 -> 2 | F9: =SUMPRODUCT(Chat_Log_Fictional!$L$3:$L$155,Chat_Log_Fictional!$F$3:$F$155)/B9 -> 4.0769231 | G9: =SUMPRODUCT(Chat_Log_Fictional!$L$3:$L$155,--(Chat_Log_Fictional!$G$3:$G$155="Y"))/B9 -> 0.15384615 | H9: =E9*(1+G9)*(5-F9) -> 2.1301775 | I9: =RANK(H9,$H$5:$H$10) -> 6
A10: Platform setup | B10: =SUM(Chat_Log_Fictional!$M$3:$M$155) -> 15 | C10: =B10/$B$2 -> 0.098039216 | D10: =SUMPRODUCT(Chat_Log_Fictional!$M$3:$M$155,Chat_Log_Fictional!$E$3:$E$155)/B10 -> 9.9333333 | E10: =B10*D10/60 -> 2.4833333 | F10: =SUMPRODUCT(Chat_Log_Fictional!$M$3:$M$155,Chat_Log_Fictional!$F$3:$F$155)/B10 -> 4.1333333 | G10: =SUMPRODUCT(Chat_Log_Fictional!$M$3:$M$155,--(Chat_Log_Fictional!$G$3:$G$155="Y"))/B10 -> 0.2 | H10: =E10*(1+G10)*(5-F10) -> 2.5826667 | I10: =RANK(H10,$H$5:$H$10) -> 5
A11: Other (no keyword matched) | B11: =COUNTIF(Chat_Log_Fictional!$N$3:$N$155,0) -> 14 | C11: =B11/$B$2 -> 0.091503268
A13: Pain score = total handling hours x (1 + repeat-contact rate) x (5 - average CSAT). It is a simple ranking aid, not a measured cost. A chat can match more than one theme, so shares add to more than 100%.
A14: Chats with no theme matched are checked by hand each week; new phrases are added to the Keywords sheet.

Sheet Weekly_Trend
A1: Chats mentioning each theme, by week (fictional data)
A2: Week | B2: Market data | C2: Account status | D2: Closure or limit reason | E2: Payout or review | F2: Sign-in or verification | G2: Platform setup
A3: 1 | B3: =SUMIFS(Chat_Log_Fictional!$H$3:$H$155,Chat_Log_Fictional!$B$3:$B$155,$A3) -> 3 | C3: =SUMIFS(Chat_Log_Fictional!$I$3:$I$155,Chat_Log_Fictional!$B$3:$B$155,$A3) -> 3 | D3: =SUMIFS(Chat_Log_Fictional!$J$3:$J$155,Chat_Log_Fictional!$B$3:$B$155,$A3) -> 3 | E3: =SUMIFS(Chat_Log_Fictional!$K$3:$K$155,Chat_Log_Fictional!$B$3:$B$155,$A3) -> 3 | F3: =SUMIFS(Chat_Log_Fictional!$L$3:$L$155,Chat_Log_Fictional!$B$3:$B$155,$A3) -> 2 | G3: =SUMIFS(Chat_Log_Fictional!$M$3:$M$155,Chat_Log_Fictional!$B$3:$B$155,$A3) -> 2
A4: 2 | B4: =SUMIFS(Chat_Log_Fictional!$H$3:$H$155,Chat_Log_Fictional!$B$3:$B$155,$A4) -> 3 | C4: =SUMIFS(Chat_Log_Fictional!$I$3:$I$155,Chat_Log_Fictional!$B$3:$B$155,$A4) -> 3 | D4: =SUMIFS(Chat_Log_Fictional!$J$3:$J$155,Chat_Log_Fictional!$B$3:$B$155,$A4) -> 3 | E4: =SUMIFS(Chat_Log_Fictional!$K$3:$K$155,Chat_Log_Fictional!$B$3:$B$155,$A4) -> 3 | F4: =SUMIFS(Chat_Log_Fictional!$L$3:$L$155,Chat_Log_Fictional!$B$3:$B$155,$A4) -> 2 | G4: =SUMIFS(Chat_Log_Fictional!$M$3:$M$155,Chat_Log_Fictional!$B$3:$B$155,$A4) -> 2
A5: 3 | B5: =SUMIFS(Chat_Log_Fictional!$H$3:$H$155,Chat_Log_Fictional!$B$3:$B$155,$A5) -> 5 | C5: =SUMIFS(Chat_Log_Fictional!$I$3:$I$155,Chat_Log_Fictional!$B$3:$B$155,$A5) -> 4 | D5: =SUMIFS(Chat_Log_Fictional!$J$3:$J$155,Chat_Log_Fictional!$B$3:$B$155,$A5) -> 3 | E5: =SUMIFS(Chat_Log_Fictional!$K$3:$K$155,Chat_Log_Fictional!$B$3:$B$155,$A5) -> 3 | F5: =SUMIFS(Chat_Log_Fictional!$L$3:$L$155,Chat_Log_Fictional!$B$3:$B$155,$A5) -> 2 | G5: =SUMIFS(Chat_Log_Fictional!$M$3:$M$155,Chat_Log_Fictional!$B$3:$B$155,$A5) -> 2
A6: 4 | B6: =SUMIFS(Chat_Log_Fictional!$H$3:$H$155,Chat_Log_Fictional!$B$3:$B$155,$A6) -> 3 | C6: =SUMIFS(Chat_Log_Fictional!$I$3:$I$155,Chat_Log_Fictional!$B$3:$B$155,$A6) -> 3 | D6: =SUMIFS(Chat_Log_Fictional!$J$3:$J$155,Chat_Log_Fictional!$B$3:$B$155,$A6) -> 3 | E6: =SUMIFS(Chat_Log_Fictional!$K$3:$K$155,Chat_Log_Fictional!$B$3:$B$155,$A6) -> 3 | F6: =SUMIFS(Chat_Log_Fictional!$L$3:$L$155,Chat_Log_Fictional!$B$3:$B$155,$A6) -> 1 | G6: =SUMIFS(Chat_Log_Fictional!$M$3:$M$155,Chat_Log_Fictional!$B$3:$B$155,$A6) -> 2
A7: 5 | B7: =SUMIFS(Chat_Log_Fictional!$H$3:$H$155,Chat_Log_Fictional!$B$3:$B$155,$A7) -> 9 | C7: =SUMIFS(Chat_Log_Fictional!$I$3:$I$155,Chat_Log_Fictional!$B$3:$B$155,$A7) -> 3 | D7: =SUMIFS(Chat_Log_Fictional!$J$3:$J$155,Chat_Log_Fictional!$B$3:$B$155,$A7) -> 3 | E7: =SUMIFS(Chat_Log_Fictional!$K$3:$K$155,Chat_Log_Fictional!$B$3:$B$155,$A7) -> 3 | F7: =SUMIFS(Chat_Log_Fictional!$L$3:$L$155,Chat_Log_Fictional!$B$3:$B$155,$A7) -> 2 | G7: =SUMIFS(Chat_Log_Fictional!$M$3:$M$155,Chat_Log_Fictional!$B$3:$B$155,$A7) -> 3
A8: 6 | B8: =SUMIFS(Chat_Log_Fictional!$H$3:$H$155,Chat_Log_Fictional!$B$3:$B$155,$A8) -> 10 | C8: =SUMIFS(Chat_Log_Fictional!$I$3:$I$155,Chat_Log_Fictional!$B$3:$B$155,$A8) -> 4 | D8: =SUMIFS(Chat_Log_Fictional!$J$3:$J$155,Chat_Log_Fictional!$B$3:$B$155,$A8) -> 4 | E8: =SUMIFS(Chat_Log_Fictional!$K$3:$K$155,Chat_Log_Fictional!$B$3:$B$155,$A8) -> 3 | F8: =SUMIFS(Chat_Log_Fictional!$L$3:$L$155,Chat_Log_Fictional!$B$3:$B$155,$A8) -> 2 | G8: =SUMIFS(Chat_Log_Fictional!$M$3:$M$155,Chat_Log_Fictional!$B$3:$B$155,$A8) -> 2
A9: 7 | B9: =SUMIFS(Chat_Log_Fictional!$H$3:$H$155,Chat_Log_Fictional!$B$3:$B$155,$A9) -> 7 | C9: =SUMIFS(Chat_Log_Fictional!$I$3:$I$155,Chat_Log_Fictional!$B$3:$B$155,$A9) -> 3 | D9: =SUMIFS(Chat_Log_Fictional!$J$3:$J$155,Chat_Log_Fictional!$B$3:$B$155,$A9) -> 2 | E9: =SUMIFS(Chat_Log_Fictional!$K$3:$K$155,Chat_Log_Fictional!$B$3:$B$155,$A9) -> 3 | F9: =SUMIFS(Chat_Log_Fictional!$L$3:$L$155,Chat_Log_Fictional!$B$3:$B$155,$A9) -> 1 | G9: =SUMIFS(Chat_Log_Fictional!$M$3:$M$155,Chat_Log_Fictional!$B$3:$B$155,$A9) -> 1
A10: 8 | B10: =SUMIFS(Chat_Log_Fictional!$H$3:$H$155,Chat_Log_Fictional!$B$3:$B$155,$A10) -> 4 | C10: =SUMIFS(Chat_Log_Fictional!$I$3:$I$155,Chat_Log_Fictional!$B$3:$B$155,$A10) -> 3 | D10: =SUMIFS(Chat_Log_Fictional!$J$3:$J$155,Chat_Log_Fictional!$B$3:$B$155,$A10) -> 2 | E10: =SUMIFS(Chat_Log_Fictional!$K$3:$K$155,Chat_Log_Fictional!$B$3:$B$155,$A10) -> 2 | F10: =SUMIFS(Chat_Log_Fictional!$L$3:$L$155,Chat_Log_Fictional!$B$3:$B$155,$A10) -> 1 | G10: =SUMIFS(Chat_Log_Fictional!$M$3:$M$155,Chat_Log_Fictional!$B$3:$B$155,$A10) -> 1
A12: Weeks 1-4 average | B12: =AVERAGE(B3:B6) -> 3.5 | C12: =AVERAGE(C3:C6) -> 3.25 | D12: =AVERAGE(D3:D6) -> 3 | E12: =AVERAGE(E3:E6) -> 3 | F12: =AVERAGE(F3:F6) -> 1.75 | G12: =AVERAGE(G3:G6) -> 2
A13: Weeks 5-7 average | B13: =AVERAGE(B7:B9) -> 8.6666667 | C13: =AVERAGE(C7:C9) -> 3.3333333 | D13: =AVERAGE(D7:D9) -> 3 | E13: =AVERAGE(E7:E9) -> 3 | F13: =AVERAGE(F7:F9) -> 1.6666667 | G13: =AVERAGE(G7:G9) -> 2
A14: Change (x) | B14: =B13/B12 -> 2.4761905 | C14: =C13/C12 -> 1.025641 | D14: =D13/D12 -> 1 | E14: =E13/E12 -> 1 | F14: =F13/F12 -> 0.95238095 | G14: =G13/G12 -> 1
A15: Alert (rise over 1.5x) | B15: =IF(B14>1.5,"Investigate","Normal") -> Investigate | C15: =IF(C14>1.5,"Investigate","Normal") -> Normal | D15: =IF(D14>1.5,"Investigate","Normal") -> Normal | E15: =IF(E14>1.5,"Investigate","Normal") -> Normal | F15: =IF(F14>1.5,"Investigate","Normal") -> Normal | G15: =IF(G14>1.5,"Investigate","Normal") -> Normal
A17: Story in the data: market-data chats jump in weeks 5-7, which is when the fictional platform update happens. This is the kind of early signal the BI team would not see in a monthly report.

Sheet Product_Roadmap
A1: From keywords to product decisions (fictional). Yellow cells are assumptions to agree with Product.
A3: Theme | B3: Evidence (live) | C3: Proposed product change | D3: Assumed reduction in chats | E3: Chats avoided per week | F3: Hours saved per week | G3: Metric to track
A4: Market data | B4: =Keyword_Analysis!B5&" of "&Keyword_Analysis!$B$2&" chats ("&TEXT(Keyword_Analysis!C5,"0%")&"), avg CSAT "&TEXT(Keyword_Analysis!F5,"0.0") -> 44 of 153 chats (29%), avg CSAT 3.5 | C4: In-app banner that shows data-feed status and a one-click 'activate market data' guide | D4: 0.4 | E4: =Keyword_Analysis!B5/8*D4 -> 2.2 | F4: =E4*Keyword_Analysis!D5/60 -> 0.49916667 | G4: Market-data chats per week
A5: Account status | B5: =Keyword_Analysis!B6&" of "&Keyword_Analysis!$B$2&" chats ("&TEXT(Keyword_Analysis!C6,"0%")&"), avg CSAT "&TEXT(Keyword_Analysis!F6,"0.0") -> 26 of 153 chats (17%), avg CSAT 4.1 | C5: Account status page that lists every account, its state and the reason | D5: 0.35 | E5: =Keyword_Analysis!B6/8*D5 -> 1.1375 | F5: =E5*Keyword_Analysis!D6/60 -> 0.23479167 | G5: Account-status chats per week
A6: Closure or limit reason | B6: =Keyword_Analysis!B7&" of "&Keyword_Analysis!$B$2&" chats ("&TEXT(Keyword_Analysis!C7,"0%")&"), avg CSAT "&TEXT(Keyword_Analysis!F7,"0.0") -> 23 of 153 chats (15%), avg CSAT 2.3 | C6: Plain-words explanation of the rule hit, with the balance and drawdown numbers, shown at the moment of the event | D6: 0.35 | E6: =Keyword_Analysis!B7/8*D6 -> 1.00625 | F6: =E6*Keyword_Analysis!D7/60 -> 0.28802083 | G6: Repeat-contact rate on this theme
A7: Payout or review | B7: =Keyword_Analysis!B8&" of "&Keyword_Analysis!$B$2&" chats ("&TEXT(Keyword_Analysis!C8,"0%")&"), avg CSAT "&TEXT(Keyword_Analysis!F8,"0.0") -> 23 of 153 chats (15%), avg CSAT 3.6 | C7: Payout tracker with stages and an expected date | D7: 0.3 | E7: =Keyword_Analysis!B8/8*D7 -> 0.8625 | F7: =E7*Keyword_Analysis!D8/60 -> 0.16 | G7: Payout chats per week; CSAT
A8: Sign-in or verification | B8: =Keyword_Analysis!B9&" of "&Keyword_Analysis!$B$2&" chats ("&TEXT(Keyword_Analysis!C9,"0%")&"), avg CSAT "&TEXT(Keyword_Analysis!F9,"0.0") -> 13 of 153 chats (8%), avg CSAT 4.1 | C8: Clearer verification messages and an in-flow re-send option | D8: 0.2 | E8: =Keyword_Analysis!B9/8*D8 -> 0.325 | F8: =E8*Keyword_Analysis!D9/60 -> 0.05 | G8: Sign-in chats per week
A9: Platform setup | B9: =Keyword_Analysis!B10&" of "&Keyword_Analysis!$B$2&" chats ("&TEXT(Keyword_Analysis!C10,"0%")&"), avg CSAT "&TEXT(Keyword_Analysis!F10,"0.0") -> 15 of 153 chats (10%), avg CSAT 4.1 | C9: Setup checklist inside the onboarding flow | D9: 0.25 | E9: =Keyword_Analysis!B10/8*D9 -> 0.46875 | F9: =E9*Keyword_Analysis!D10/60 -> 0.077604167 | G9: Setup chats from new clients
A10: Total | E10: =SUM(E4:E9) -> 6 | F10: =SUM(F4:F9) -> 1.3095833
A12: Chats avoided = chats in the sample / 8 weeks x assumed reduction. Assumed reductions are planning guesses, not forecasts; they would be replaced by a pilot result.
